py_module_boilerplate/__init__.py
py_module_boilerplate/main.py
py_module_boilerplate/version.py
py_module_boilerplate-0.0.4.dist-info/LICENSE
py_module_boilerplate-0.0.4.dist-info/METADATA
py_module_boilerplate-0.0.4.dist-info/WHEEL
py_module_boilerplate-0.0.4.dist-info/entry_points.txt
py_module_boilerplate-0.0.4.dist-info/top_level.txt
py_module_boilerplate-0.0.4.dist-info/RECORD
