Metadata-Version: 2.1
Name: py-module-boilerplate
Version: 0.0.4
Summary: 
Provides-Extra: develop
Requires-Dist: coverage; extra == 'develop'
Requires-Dist: flake8-import-order; extra == 'develop'
Requires-Dist: pylama; extra == 'develop'
Requires-Dist: pytest-asyncio; extra == 'develop'
Requires-Dist: pytest-cov; extra == 'develop'
Requires-Dist: pytest; extra == 'develop'
Requires-Dist: tox; extra == 'develop'
Requires-Dist: twine; extra == 'develop'
